{"chunk_definitions":[{"row":7,"row_count":1,"visible":true,"expansion_state":0,"options":{"engine":"r","label":"unnamed-chunk-63","dev":"png"},"document_id":"A2E23844","chunk_id":"ct7i2id3h2mcy","chunk_label":"unnamed-chunk-1"},{"row":11,"row_count":1,"visible":true,"expansion_state":0,"options":{"engine":"r","label":"unnamed-chunk-64","dev":"png"},"document_id":"A2E23844","chunk_id":"ciofhp4y6wybb","chunk_label":"unnamed-chunk-2"},{"row":18,"row_count":1,"visible":true,"expansion_state":0,"options":{"engine":"r","label":"unnamed-chunk-65","dev":"png"},"document_id":"A2E23844","chunk_id":"c8apsuejsn1ez","chunk_label":"unnamed-chunk-3"},{"row":54,"row_count":1,"visible":true,"expansion_state":0,"options":{"engine":"r","label":"unnamed-chunk-66","dev":"png"},"document_id":"A2E23844","chunk_id":"c3t2rkj8pfllm","chunk_label":"unnamed-chunk-4"},{"row":58,"row_count":1,"visible":true,"expansion_state":0,"options":{"engine":"r","label":"unnamed-chunk-67","dev":"png"},"document_id":"A2E23844","chunk_id":"c5xh9g3kt6gjz","chunk_label":"unnamed-chunk-5"},{"row":69,"row_count":1,"visible":true,"expansion_state":0,"options":{"engine":"r","label":"unnamed-chunk-68","dev":"png"},"document_id":"A2E23844","chunk_id":"cpin2v1jiw94q","chunk_label":"unnamed-chunk-6"},{"row":76,"row_count":1,"visible":true,"expansion_state":0,"options":{"engine":"r","label":"unnamed-chunk-69","dev":"png"},"document_id":"A2E23844","chunk_id":"cgwjzwn4ejfbz","chunk_label":"unnamed-chunk-7"},{"row":88,"row_count":1,"visible":true,"expansion_state":0,"options":{},"document_id":"A2E23844","chunk_id":"c22vonv26a3n7","chunk_label":"unnamed-chunk-8"},{"row":103,"row_count":1,"visible":true,"expansion_state":0,"options":{},"document_id":"A2E23844","chunk_id":"ctutsw9qnrp4f","chunk_label":"unnamed-chunk-9"},{"row":116,"row_count":1,"visible":true,"expansion_state":0,"options":{},"document_id":"A2E23844","chunk_id":"c53rgv9ef5wjx","chunk_label":"unnamed-chunk-10"},{"row":123,"row_count":1,"visible":true,"expansion_state":0,"options":{},"document_id":"A2E23844","chunk_id":"c5aia9bydsu40","chunk_label":"unnamed-chunk-11"},{"row":136,"row_count":1,"visible":true,"expansion_state":0,"options":{},"document_id":"A2E23844","chunk_id":"conq6tdbra5ej","chunk_label":"unnamed-chunk-12"},{"row":144,"row_count":1,"visible":true,"expansion_state":0,"options":{},"document_id":"A2E23844","chunk_id":"c9kw475xo78kg","chunk_label":"unnamed-chunk-13"},{"row":158,"row_count":1,"visible":true,"expansion_state":0,"options":{},"document_id":"A2E23844","chunk_id":"cehowvhetmvv0","chunk_label":"unnamed-chunk-14"},{"row":170,"row_count":1,"visible":true,"expansion_state":0,"options":{},"document_id":"A2E23844","chunk_id":"cw16fkbz1et6s","chunk_label":"unnamed-chunk-15"},{"row":181,"row_count":1,"visible":true,"expansion_state":0,"options":{},"document_id":"A2E23844","chunk_id":"cbgwpt7occ8nr","chunk_label":"unnamed-chunk-16"},{"row":193,"row_count":1,"visible":true,"expansion_state":0,"options":{},"document_id":"A2E23844","chunk_id":"ce2tc4mcc8of9","chunk_label":"unnamed-chunk-17"},{"row":204,"row_count":1,"visible":true,"expansion_state":0,"options":{},"document_id":"A2E23844","chunk_id":"c0iqp0ne0s48x","chunk_label":"unnamed-chunk-18"}],"doc_write_time":1729307437}